btklog/__init__.py
btklog/btklog.py
btklog-1.0.2.dist-info/LICENSE
btklog-1.0.2.dist-info/METADATA
btklog-1.0.2.dist-info/WHEEL
btklog-1.0.2.dist-info/entry_points.txt
btklog-1.0.2.dist-info/top_level.txt
btklog-1.0.2.dist-info/RECORD
