Metadata-Version: 2.1
Name: btklog
Version: 1.0.2
Summary: Generates IP logs compatible with Turkey 5651 law from dhcpd.leases format.
Home-page: https://github.com/acikogun/btklog
Author: Ogun Acik
Author-email: acikogun@gmail.com
License: Apache License 2.0
Platform: UNKNOWN
Classifier: Intended Audience :: Developers
Classifier: Intended Audience :: System Administrators
Classifier: Natural Language :: Turkish
Classifier: License :: OSI Approved :: Apache Software License
Classifier: Programming Language :: Python
Classifier: Programming Language :: Python :: 2
Classifier: Programming Language :: Python :: 2.7
Classifier: Programming Language :: Python :: 3
Classifier: Programming Language :: Python :: 3.4
Classifier: Programming Language :: Python :: 3.5
Classifier: Programming Language :: Python :: 3.6
Classifier: Programming Language :: Python :: 3.7
Classifier: Programming Language :: Python :: 3.8
Requires-Dist: Click
Requires-Dist: dhcp-leases
